[
    {
        "id": 1,
        "brand": "Nike",
        "model": "Air Force Travis Scott",
        "precio": 120,
        "img": "../../assets/img/travis-scott.jpg"
    },
    {
        "id": 2,
        "brand": "Nike",
        "model": "Air One MID",
        "precio": 150,
        "img": "../../assets/img/air1mid.jpg"
    },
    {
        "id": 3,
        "brand": "Nike",
        "model": "Air ONE",
        "precio": 110,
        "img": "../../assets/img/product-img2.jpg"
    },
    {
        "id": 4,
        "brand": "Nike",
        "model": "Air Force",
        "precio": 100,
        "img": "../../assets/img/product-img3.jpg"
    },
    {
        "id": 5,
        "brand": "Nike",
        "model": "Running",
        "precio": 80,
        "img": "../../assets/img/product-img4.jpg"
    },
    {
        "id": 6,
        "brand": "Nike",
        "model": "Shox",
        "precio": 100,
        "img": "../../assets/img/product-img5.jpg"
    }
]